notehub_py/__init__.py
notehub_py/api_client.py
notehub_py/api_response.py
notehub_py/configuration.py
notehub_py/exceptions.py
notehub_py/py.typed
notehub_py/rest.py
notehub_py/api/__init__.py
notehub_py/api/alert_api.py
notehub_py/api/authorization_api.py
notehub_py/api/billing_account_api.py
notehub_py/api/device_api.py
notehub_py/api/event_api.py
notehub_py/api/external_devices_api.py
notehub_py/api/monitor_api.py
notehub_py/api/project_api.py
notehub_py/api/route_api.py
notehub_py/api/usage_api.py
notehub_py/api/webhook_api.py
notehub_py/models/__init__.py
notehub_py/models/add_device_to_fleets_request.py
notehub_py/models/alert.py
notehub_py/models/alert_data_inner.py
notehub_py/models/alert_notifications_inner.py
notehub_py/models/aws_route.py
notehub_py/models/azure_route.py
notehub_py/models/billing_account.py
notehub_py/models/billing_account_role.py
notehub_py/models/blynk_route.py
notehub_py/models/body.py
notehub_py/models/cellular_plan.py
notehub_py/models/clone_project_request.py
notehub_py/models/contact.py
notehub_py/models/create_fleet_request.py
notehub_py/models/create_monitor.py
notehub_py/models/create_product_request.py
notehub_py/models/create_project_request.py
notehub_py/models/create_update_repository.py
notehub_py/models/current_firmware.py
notehub_py/models/data_field.py
notehub_py/models/data_set_field.py
notehub_py/models/data_usage.py
notehub_py/models/datacake_route.py
notehub_py/models/delete_device_from_fleets_request.py
notehub_py/models/delete_notefiles_request.py
notehub_py/models/device.py
notehub_py/models/device_dfu_history.py
notehub_py/models/device_dfu_history_current.py
notehub_py/models/device_dfu_history_page.py
notehub_py/models/device_dfu_state_machine.py
notehub_py/models/device_dfu_state_machine_node.py
notehub_py/models/device_dfu_status.py
notehub_py/models/device_dfu_status_page.py
notehub_py/models/device_session.py
notehub_py/models/device_tower_info.py
notehub_py/models/device_usage.py
notehub_py-5.0.0.dist-info/METADATA
notehub_py-5.0.0.dist-info/WHEEL
notehub_py-5.0.0.dist-info/top_level.txt
notehub_py-5.0.0.dist-info/RECORD
