Metadata-Version: 2.4
Name: notehub-py
Version: 5.0.0
Summary: Python-based library for accessing the Blues Notehub API.
Home-page: https://github.com/blues/notehub-py
Author: Blues Engineering
Author-email: engineering@blues.io
Keywords: OpenAPI,OpenAPI-Generator,Notehub API
Classifier: Programming Language :: Python
Classifier: Programming Language :: Python :: 3.7
Classifier: Programming Language :: Python :: 3.8
Classifier: Programming Language :: Python :: 3.9
Classifier: Programming Language :: Python :: 3.11
Classifier: License :: OSI Approved :: MIT License
Classifier: Operating System :: OS Independent
Classifier: Intended Audience :: Developers
Classifier: Natural Language :: English
Requires-Dist: urllib3>=2.5.0
Requires-Dist: python-dateutil
Requires-Dist: pydantic>=2
Requires-Dist: typing-extensions>=4.7.1
Dynamic: author
Dynamic: author-email
Dynamic: classifier
Dynamic: description
Dynamic: description-content-type
Dynamic: home-page
Dynamic: keywords
Dynamic: requires-dist
Dynamic: summary
